pydra/tasks/fastsurfer/__init__.py
pydra/tasks/fastsurfer/_version.py
pydra/tasks/fastsurfer/latest.py
pydra/tasks/fastsurfer/v2_2/__init__.py
pydra/tasks/fastsurfer/v2_2/tests/conftest.py
pydra/tasks/fastsurfer/v2_2/tests/test_fastsurfer.py
pydra_tasks_fastsurfer-0.2.2.dist-info/METADATA
pydra_tasks_fastsurfer-0.2.2.dist-info/WHEEL
pydra_tasks_fastsurfer-0.2.2.dist-info/licenses/LICENSE
pydra_tasks_fastsurfer-0.2.2.dist-info/RECORD
